{"kills":10,"score":593,"bagSize":6,"money":31,"name":"God","bag":["Legend-hoo","Legend-hoo","Super-hoo","Stick","Legend-hoo","Mega-hoo"],"team":[{"stats":[169,169,169,186],"attacks":["Soft Slap","Shoulder Bash","Stoic","High Kick","Dark Energy","Hyper Impact","Jaw Breaker","Tornado Kick"],"name":"Dog","xp":0,"ID":null,"tempStats":[169,169,169,186],"holdItem":"Whistle-hoo"},{"stats":[167,167,167,127],"attacks":["Soft Slap","High Kick","Jaw Breaker","Flurry Fist","Dark Energy","Hyper Impact"],"name":"Sirtequl","xp":0,"ID":null,"tempStats":[167,167,167,127],"holdItem":"Smoke bomb"},{"stats":[30,50,20,50],"attacks":["High Kick","Stoic"],"name":"Chamarrden","xp":0,"ID":null,"tempStats":[30,50,20,50],"holdItem":"Super-hoo"},{"stats":[85,32,64,53],"attacks":["Stoic","Jaw Breaker","Shoulder Bash"],"name":"Grarevel","xp":0,"ID":null,"tempStats":[85,32,64,53],"holdItem":"Mega-hoo"},{"stats":[58,58,43,72],"attacks":["Stoic","Shoulder Bash"],"name":"Bazut","xp":0,"ID":null,"tempStats":[58,58,43,72],"holdItem":null},{"stats":[73,55,128,18],"attacks":["Soft Slap","Stoic"],"name":"Baublusar","xp":0,"ID":null,"tempStats":[73,55,128,18],"holdItem":null}],"xpShare":true}